ml_observability/__init__.py
ml_observability/core/__init__.py
ml_observability/core/exceptions.py
ml_observability/core/mlflow_client.py
ml_observability/observability/__init__.py
ml_observability/observability/async_monitor.py
ml_observability/observability/base_tracer.py
ml_observability/observability/client_wrappers.py
ml_observability/observability/cost_tracking.py
ml_observability/observability/langflow_async_tracer.py
ml_observability/observability/monitor.py
ml_observability/py.typed
ml_observability/utils/__init__.py
ml_observability/utils/logger.py
ml_observability/version.py
ml_observability/visualization/__init__.py
ml_observability/visualization/cost_visualization.py
autonomize_ml_observability-1.2.15.dist-info/METADATA
autonomize_ml_observability-1.2.15.dist-info/WHEEL
autonomize_ml_observability-1.2.15.dist-info/RECORD
