Metadata-Version: 2.1
Name: autonomize-ml-observability
Version: 1.2.15
Summary: Comprehensive LLM observability SDK with tracing, monitoring, and cost tracking
Home-page: https://github.com/autonomize-ai/autonomize-ml-observability.git
License: Proprietary
Keywords: mlflow,llm,observability,cost tracking,monitoring
Author: Jagveer Singh
Author-email: jagveer@autonomize.ai
Requires-Python: >=3.12,<4.0
Classifier: License :: Other/Proprietary License
Classifier: Programming Language :: Python :: 3
Classifier: Programming Language :: Python :: 3.12
Provides-Extra: anthropic
Provides-Extra: modelhub
Provides-Extra: openai
Requires-Dist: anthropic (>=0.49.0,<0.50.0) ; extra == "anthropic"
Requires-Dist: autonomize-core (>=0.1.7,<0.2.0)
Requires-Dist: azure-identity (>=1.21.0,<2.0.0)
Requires-Dist: azure-storage-blob (>=12.25.1,<13.0.0)
Requires-Dist: httpx (>=0.28.1,<0.29.0) ; extra == "modelhub"
Requires-Dist: mlflow (>=3.1)
Requires-Dist: openai (>=1.43.0,<2.0.0) ; extra == "openai"
Requires-Dist: pandas (>=2.2.2,<3.0.0)
Requires-Dist: tenacity (>=8.2.3,<10.0.0)
Requires-Dist: tiktoken (>=0.7.0)
Project-URL: Repository, https://github.com/autonomize-ai/autonomize-ml-observability.git
